{
   "LIBRARY": [
      {
         "level": "A",
         "bay": "0",
         "reservations": [
            {
               "time": {
                  "start": "2022-05-14T23:00:00.000Z",
                  "duration": {
                     "hr": 1,
                     "min": 0
                  }
               },
               "user": {
                  "name": "Caleb Adeyemo",
                  "email": "ygb19mzu@uea.ac.uk",
                  "password": null
               }
            }
         ]
      },
      {
         "level": "A",
         "bay": "1",
         "reservations": []
      },
      {
         "level": "A",
         "bay": "2",
         "reservations": []
      },
      {
         "level": "A",
         "bay": "3",
         "reservations": []
      },
      {
         "level": "A",
         "bay": "4",
         "reservations": []
      },
      {
         "level": "A",
         "bay": "5",
         "reservations": []
      },
      {
         "level": "A",
         "bay": "6",
         "reservations": []
      },
      {
         "level": "A",
         "bay": "7",
         "reservations": []
      },
      {
         "level": "A",
         "bay": "8",
         "reservations": []
      },
      {
         "level": "A",
         "bay": "9",
         "reservations": []
      }
   ],
   "SU": [
      {
         "level": "A",
         "bay": "0",
         "reservations": []
      },
      {
         "level": "A",
         "bay": "1",
         "reservations": []
      },
      {
         "level": "A",
         "bay": "2",
         "reservations": []
      },
      {
         "level": "A",
         "bay": "3",
         "reservations": []
      },
      {
         "level": "A",
         "bay": "4",
         "reservations": []
      },
      {
         "level": "A",
         "bay": "5",
         "reservations": []
      },
      {
         "level": "A",
         "bay": "6",
         "reservations": []
      },
      {
         "level": "A",
         "bay": "7",
         "reservations": []
      },
      {
         "level": "A",
         "bay": "8",
         "reservations": []
      },
      {
         "level": "A",
         "bay": "9",
         "reservations": []
      }
   ],
   "VILLAGE": [
      {
         "level": "A",
         "bay": "0",
         "reservations": [
            {
               "time": {
                  "start": "2022-05-16T23:00:00.000Z",
                  "duration": {
                     "hr": 1,
                     "min": 0
                  }
               },
               "user": {
                  "name": "caleb adeyemo",
                  "email": "oldercalebadeyemo2@gmail.com",
                  "password": null
               }
            },
            {
               "time": {
                  "start": "2022-05-18T01:00:00.000Z",
                  "duration": {
                     "hr": 3,
                     "min": 0
                  }
               },
               "user": {
                  "name": "Bot",
                  "email": "tadeyemo511@gmail.com",
                  "password": null
               }
            }
         ]
      },
      {
         "level": "A",
         "bay": "1",
         "reservations": []
      },
      {
         "level": "A",
         "bay": "2",
         "reservations": []
      },
      {
         "level": "A",
         "bay": "3",
         "reservations": []
      },
      {
         "level": "A",
         "bay": "4",
         "reservations": []
      },
      {
         "level": "A",
         "bay": "5",
         "reservations": []
      },
      {
         "level": "A",
         "bay": "6",
         "reservations": []
      },
      {
         "level": "A",
         "bay": "7",
         "reservations": []
      },
      {
         "level": "A",
         "bay": "8",
         "reservations": []
      },
      {
         "level": "A",
         "bay": "9",
         "reservations": []
      }
   ],
   "SPORTSPARK": [
      {
         "level": "A",
         "bay": "0",
         "reservations": []
      },
      {
         "level": "A",
         "bay": "1",
         "reservations": []
      },
      {
         "level": "A",
         "bay": "2",
         "reservations": []
      },
      {
         "level": "A",
         "bay": "3",
         "reservations": []
      },
      {
         "level": "A",
         "bay": "4",
         "reservations": []
      },
      {
         "level": "A",
         "bay": "5",
         "reservations": []
      },
      {
         "level": "A",
         "bay": "6",
         "reservations": []
      },
      {
         "level": "A",
         "bay": "7",
         "reservations": []
      },
      {
         "level": "A",
         "bay": "8",
         "reservations": []
      },
      {
         "level": "A",
         "bay": "9",
         "reservations": []
      }
   ],
   "NEW_SCI": [
      {
         "level": "A",
         "bay": "0",
         "reservations": [
            {
               "time": {
                  "start": "2022-05-14T23:00:00.000Z",
                  "duration": {
                     "hr": 1,
                     "min": 0
                  }
               },
               "user": {
                  "name": "caleb adeyemo",
                  "email": "ygb19mzu@uea.ac.uk",
                  "password": null
               }
            },
            {
               "time": {
                  "start": "2022-05-16T23:00:00.000Z",
                  "duration": {
                     "hr": 1,
                     "min": 0
                  }
               },
               "user": {
                  "name": "Bot",
                  "email": "tadeyemo511@gmail.com",
                  "password": null
               }
            }
         ]
      },
      {
         "level": "A",
         "bay": "1",
         "reservations": []
      },
      {
         "level": "A",
         "bay": "2",
         "reservations": []
      },
      {
         "level": "A",
         "bay": "3",
         "reservations": []
      },
      {
         "level": "A",
         "bay": "4",
         "reservations": []
      },
      {
         "level": "A",
         "bay": "5",
         "reservations": []
      },
      {
         "level": "A",
         "bay": "6",
         "reservations": []
      },
      {
         "level": "A",
         "bay": "7",
         "reservations": []
      },
      {
         "level": "A",
         "bay": "8",
         "reservations": []
      },
      {
         "level": "A",
         "bay": "9",
         "reservations": []
      }
   ],
   "INTO": [
      {
         "level": "A",
         "bay": "0",
         "reservations": []
      },
      {
         "level": "A",
         "bay": "1",
         "reservations": []
      },
      {
         "level": "A",
         "bay": "2",
         "reservations": []
      },
      {
         "level": "A",
         "bay": "3",
         "reservations": []
      },
      {
         "level": "A",
         "bay": "4",
         "reservations": []
      },
      {
         "level": "A",
         "bay": "5",
         "reservations": []
      },
      {
         "level": "A",
         "bay": "6",
         "reservations": []
      },
      {
         "level": "A",
         "bay": "7",
         "reservations": []
      },
      {
         "level": "A",
         "bay": "8",
         "reservations": []
      },
      {
         "level": "A",
         "bay": "9",
         "reservations": []
      }
   ],
   "SAINSBURY": [
      {
         "level": "A",
         "bay": "0",
         "reservations": []
      },
      {
         "level": "A",
         "bay": "1",
         "reservations": []
      },
      {
         "level": "A",
         "bay": "2",
         "reservations": []
      },
      {
         "level": "A",
         "bay": "3",
         "reservations": []
      },
      {
         "level": "A",
         "bay": "4",
         "reservations": []
      },
      {
         "level": "A",
         "bay": "5",
         "reservations": []
      },
      {
         "level": "A",
         "bay": "6",
         "reservations": []
      },
      {
         "level": "A",
         "bay": "7",
         "reservations": []
      },
      {
         "level": "A",
         "bay": "8",
         "reservations": []
      },
      {
         "level": "A",
         "bay": "9",
         "reservations": []
      }
   ]
}